Metadata-Version: 1.2
Name: obj-detector-setup
Version: 0.1
Summary: Detector setup
Home-page: UNKNOWN
License: UNKNOWN
Platform: UNKNOWN
Requires-Python: >3.6
